seqlike/AlignCommandline.py
seqlike/FreeMono.ttf
seqlike/Mutation.py
seqlike/MutationSet.py
seqlike/SeqLike.py
seqlike/SeqLikeAccessor.py
seqlike/SequenceLike.py
seqlike/__init__.py
seqlike/alignment_commands.py
seqlike/alignment_utils.py
seqlike/alphabets.py
seqlike/codon_tables.py
seqlike/draw_utils.py
seqlike/encoders.py
seqlike/version.py
seqlike/utils/__init__.py
seqlike/utils/constructor.py
seqlike/utils/sequences.py
seqlike/utils/validation.py
tests/__init__.py
tests/test_Mutation.py
tests/test_SeqLike.py
tests/test_SeqLikeAccessor.py
tests/test_SeqLike_alignment.py
tests/test_SeqLike_conversion_to_numerical.py
tests/test_SeqLike_magic_methods.py
tests/test_SeqLike_to_other_seq_formats.py
tests/test_SequenceLike.py
tests/test_aaSeqLike_ntSeqLike.py
tests/test_assets.py
tests/test_codon_tables.py
tests/test_draw_utils.py
tests/test_encoders.py
tests/test_identify_alphabet.py
seqlike-1.5.4.dist-info/LICENSE
seqlike-1.5.4.dist-info/METADATA
seqlike-1.5.4.dist-info/WHEEL
seqlike-1.5.4.dist-info/top_level.txt
seqlike-1.5.4.dist-info/RECORD
