Metadata-Version: 2.1
Name: seqlike
Version: 1.5.4
Home-page: https://github.com/modernatx/seqlike
Project-URL: Documentation, https://modernatx.github.io/seqlike
Project-URL: Source Code, https://github.com/modernatx/seqlike
Project-URL: Issue Tracker, https://github.com/modernatx/seqlike/issues
Classifier: Intended Audience :: Science/Research
Classifier: Operating System :: OS Independent
Classifier: Programming Language :: Python :: 3
Classifier: Programming Language :: Python :: 3.7
Classifier: Programming Language :: Python :: 3.8
Classifier: Programming Language :: Python :: 3.9
Classifier: Topic :: Scientific/Engineering
License-File: LICENSE
Requires-Dist: Pillow
Requires-Dist: biopython
Requires-Dist: lazy-loader
Requires-Dist: multipledispatch
Requires-Dist: numpy
Requires-Dist: pandas
Requires-Dist: python-codon-tables
Requires-Dist: scikit-learn
Requires-Dist: weblogo
